odoo/addons/product_intercompany_account/README.rst
odoo/addons/product_intercompany_account/__init__.py
odoo/addons/product_intercompany_account/__manifest__.py
odoo/addons/product_intercompany_account/i18n/product_intercompany_account.pot
odoo/addons/product_intercompany_account/models/__init__.py
odoo/addons/product_intercompany_account/models/account_invoice.py
odoo/addons/product_intercompany_account/models/account_invoice_line.py
odoo/addons/product_intercompany_account/models/product_category.py
odoo/addons/product_intercompany_account/models/product_template.py
odoo/addons/product_intercompany_account/models/sale_order_line.py
odoo/addons/product_intercompany_account/readme/CONTRIBUTORS.rst
odoo/addons/product_intercompany_account/readme/DESCRIPTION.rst
odoo/addons/product_intercompany_account/static/description/icon.png
odoo/addons/product_intercompany_account/static/description/index.html
odoo/addons/product_intercompany_account/tests/__init__.py
odoo/addons/product_intercompany_account/tests/test_intercompany_accounts.py
odoo/addons/product_intercompany_account/views/product_view.xml
odoo12_addon_product_intercompany_account-12.0.1.0.4.dist-info/METADATA
odoo12_addon_product_intercompany_account-12.0.1.0.4.dist-info/WHEEL
odoo12_addon_product_intercompany_account-12.0.1.0.4.dist-info/top_level.txt
odoo12_addon_product_intercompany_account-12.0.1.0.4.dist-info/RECORD
